binstandard/__init__.py
binstandard/cli.py
binstandard/client.py
binstandard-0.1.0.dist-info/METADATA
binstandard-0.1.0.dist-info/WHEEL
binstandard-0.1.0.dist-info/entry_points.txt
binstandard-0.1.0.dist-info/top_level.txt
binstandard-0.1.0.dist-info/RECORD
