Metadata-Version: 2.4
Name: BinStandard
Version: 0.1.0
Summary: An Simple Library With Fetch Bin info With binlist.net, Fully Asyncio With Uvloop Power.
Home-page: https://github.com/yourusername/BinStandard
Author: @Nactire
Classifier: Programming Language :: Python :: 3
Classifier: License :: OSI Approved :: MIT License
Classifier: Operating System :: OS Independent
Requires-Python: >=3.8
Requires-Dist: aiohttp
Requires-Dist: uvloop
Dynamic: author
Dynamic: classifier
Dynamic: description
Dynamic: description-content-type
Dynamic: home-page
Dynamic: requires-dist
Dynamic: requires-python
Dynamic: summary
